setup.py
dist_prob_123/Binomialdistribution.py
dist_prob_123/Gaussiandistribution.py
dist_prob_123/Generaldistribution.py
dist_prob_123/__init__.py
dist_prob_123.egg-info/PKG-INFO
dist_prob_123.egg-info/SOURCES.txt
dist_prob_123.egg-info/dependency_links.txt
dist_prob_123.egg-info/not-zip-safe
dist_prob_123.egg-info/top_level.txt